pylmscontroller/__init__.py
pylmscontroller/pylmscontroller.py
pylmscontroller-1.0.0.dist-info/COPYING
pylmscontroller-1.0.0.dist-info/COPYING.LESSER
pylmscontroller-1.0.0.dist-info/LICENSE
pylmscontroller-1.0.0.dist-info/METADATA
pylmscontroller-1.0.0.dist-info/WHEEL
pylmscontroller-1.0.0.dist-info/RECORD
