Metadata-Version: 2.3
Name: pylmscontroller
Version: 1.0.0
Summary: Python library for Alphanov's LMS Controller
License: LGPL-3.0-or-later
Author: mmouchous-ledger
Author-email: michael.mouchous@ledger.fr
Requires-Python: >=3.9
Classifier: License :: OSI Approved :: GNU Lesser General Public License v3 or later (LGPLv3+)
Classifier: Programming Language :: Python :: 3
Classifier: Programming Language :: Python :: 3.9
Classifier: Programming Language :: Python :: 3.10
Classifier: Programming Language :: Python :: 3.11
Classifier: Programming Language :: Python :: 3.12
Classifier: Programming Language :: Python :: 3.13
Requires-Dist: pyserial (>=3.5,<4.0)
